jgcmlib/__init__.py
jgcmlib/jgabcli.py
jgcmlib/jgcmhelper.py
jgcmlib-1.0.59.dist-info/LICENSE
jgcmlib-1.0.59.dist-info/METADATA
jgcmlib-1.0.59.dist-info/WHEEL
jgcmlib-1.0.59.dist-info/entry_points.txt
jgcmlib-1.0.59.dist-info/top_level.txt
jgcmlib-1.0.59.dist-info/RECORD
